cdd_agent/__init__.py
cdd_agent/__main__.py
cdd_agent/agent.py
cdd_agent/agents/__init__.py
cdd_agent/agents/executor.py
cdd_agent/agents/planner.py
cdd_agent/agents/socrates.py
cdd_agent/agents/test_agent.py
cdd_agent/agents/writer.py
cdd_agent/approval.py
cdd_agent/auth.py
cdd_agent/background_executor.py
cdd_agent/cli.py
cdd_agent/config.py
cdd_agent/context.py
cdd_agent/logging.py
cdd_agent/mechanical/__init__.py
cdd_agent/mechanical/init.py
cdd_agent/mechanical/new_ticket.py
cdd_agent/mechanical/templates/en/bug-plan-template.md
cdd_agent/mechanical/templates/en/bug-ticket-template.yaml
cdd_agent/mechanical/templates/en/constitution-template.md
cdd_agent/mechanical/templates/en/enhancement-plan-template.md
cdd_agent/mechanical/templates/en/enhancement-ticket-template.yaml
cdd_agent/mechanical/templates/en/feature-doc-template.md
cdd_agent/mechanical/templates/en/feature-plan-template.md
cdd_agent/mechanical/templates/en/feature-ticket-template.yaml
cdd_agent/mechanical/templates/en/guide-doc-template.md
cdd_agent/mechanical/templates/en/spike-plan-template.md
cdd_agent/mechanical/templates/en/spike-ticket-template.yaml
cdd_agent/oauth.py
cdd_agent/session/__init__.py
cdd_agent/session/base_agent.py
cdd_agent/session/chat_session.py
cdd_agent/slash_commands/__init__.py
cdd_agent/slash_commands/base.py
cdd_agent/slash_commands/exec_command.py
cdd_agent/slash_commands/help_command.py
cdd_agent/slash_commands/init_command.py
cdd_agent/slash_commands/new_command.py
cdd_agent/slash_commands/plan_command.py
cdd_agent/slash_commands/router.py
cdd_agent/slash_commands/socrates_command.py
cdd_agent/tools.py
cdd_agent/tui.py
cdd_agent/ui.py
cdd_agent/utils/__init__.py
cdd_agent/utils/custom_markdown.py
cdd_agent/utils/execution_state.py
cdd_agent/utils/filtered_tools.py
cdd_agent/utils/markdown_normalizer.py
cdd_agent/utils/plan_model.py
cdd_agent/utils/yaml_parser.py
cdd_agent-0.0.5.dist-info/LICENSE
cdd_agent-0.0.5.dist-info/METADATA
cdd_agent-0.0.5.dist-info/WHEEL
cdd_agent-0.0.5.dist-info/entry_points.txt
cdd_agent-0.0.5.dist-info/RECORD
