Metadata-Version: 2.3
Name: cdd-agent
Version: 0.0.5
Summary: AI coding assistant with structured CDD workflows - LLM agnostic terminal agent
License: MIT
Keywords: ai,llm,coding-assistant,anthropic,openai,cli,agent
Author: Guilherme Gouw
Author-email: guilherme.gouw@gmail.com
Requires-Python: >=3.10,<4.0
Classifier: Development Status :: 3 - Alpha
Classifier: Intended Audience :: Developers
Classifier: License :: OSI Approved :: MIT License
Classifier: Programming Language :: Python :: 3
Classifier: Programming Language :: Python :: 3.10
Classifier: Programming Language :: Python :: 3.11
Classifier: Programming Language :: Python :: 3.12
Classifier: Programming Language :: Python :: 3.13
Classifier: Topic :: Software Development :: Code Generators
Classifier: Topic :: Software Development :: Libraries :: Python Modules
Requires-Dist: anthropic (>=0.40.0,<0.41.0)
Requires-Dist: authlib (>=1.3.2,<2.0.0)
Requires-Dist: catppuccin[pygments] (>=2.5.0,<3.0.0)
Requires-Dist: click (>=8.1.7,<9.0.0)
Requires-Dist: httpx (>=0.27.0,<0.28.0)
Requires-Dist: openai (>=1.55.0,<2.0.0)
Requires-Dist: pydantic (>=2.10.0,<3.0.0)
Requires-Dist: python-dotenv (>=1.0.0,<2.0.0)
Requires-Dist: pyyaml (>=6.0.1,<7.0.0)
Requires-Dist: rich (>=13.7.0,<14.0.0)
Requires-Dist: textual (>=0.87.1,<0.88.0)
Project-URL: Homepage, https://github.com/guilhermegouw/context-driven-development-agent
Project-URL: Repository, https://github.com/guilhermegouw/context-driven-development-agent
